irmacl_async/__init__.py
irmacl_async/apiclient.py
irmacl_async-3.2.0.dist-info/AUTHORS
irmacl_async-3.2.0.dist-info/LICENSE
irmacl_async-3.2.0.dist-info/METADATA
irmacl_async-3.2.0.dist-info/WHEEL
irmacl_async-3.2.0.dist-info/top_level.txt
irmacl_async-3.2.0.dist-info/RECORD
