Metadata-Version: 2.1
Name: irmacl-async
Version: 3.2.0
Summary: Irma asynchronous command line tool for API v3
Home-page: https://github.com/quarkslab/irmacl-async
Author: irma-dev
Author-email: irma-dev@quarkslab.com
License: ApacheV2
Platform: UNKNOWN
Requires-Dist: aiohttp (==3.6.2)
Requires-Dist: irma-shared (==3.3.0)
Requires-Dist: pyyaml
